[
  {
    "writing_date": "2025-08-07",
    "word_count": 137287,
    "words_written": 0,
    "previous_date": null,
    "previous_count": null,
    "note": "Reconstructed from old data"
  },
  {
    "writing_date": "2025-08-08",
    "word_count": 137581,
    "words_written": 294,
    "previous_date": "2025-08-07",
    "previous_count": 137287
  },
  {
    "writing_date": "2025-08-11",
    "word_count": 138331,
    "words_written": 750,
    "previous_date": "2025-08-08",
    "previous_count": 137581
  },
  {
    "writing_date": "2025-08-12",
    "word_count": 138834,
    "words_written": 503,
    "previous_date": "2025-08-11",
    "previous_count": 138331
  },
  {
    "writing_date": "2025-08-13",
    "word_count": 139999,
    "words_written": 1165,
    "previous_date": "2025-08-12",
    "previous_count": 138834
  },
  {
    "writing_date": "2025-08-14",
    "word_count": 140793,
    "words_written": 794,
    "previous_date": "2025-08-13",
    "previous_count": 139999
  },
  {
    "writing_date": "2025-08-15",
    "word_count": 141114,
    "words_written": 321,
    "previous_date": "2025-08-14",
    "previous_count": 140793
  },
  {
    "writing_date": "2025-08-16",
    "word_count": 141426,
    "words_written": 312,
    "previous_date": "2025-08-15",
    "previous_count": 141114
  },
  {
    "writing_date": "2025-08-20",
    "word_count": 141551,
    "words_written": 125,
    "previous_date": "2025-08-16",
    "previous_count": 141426
  },
  {
    "writing_date": "2025-08-21",
    "word_count": 141638,
    "words_written": 87,
    "previous_date": "2025-08-20",
    "previous_count": 141551
  },
  {
    "writing_date": "2025-08-22",
    "word_count": 141797,
    "words_written": 159,
    "previous_date": "2025-08-21",
    "previous_count": 141638
  },
  {
    "writing_date": "2025-08-23",
    "word_count": 142195,
    "words_written": 398,
    "previous_date": "2025-08-22",
    "previous_count": 141797
  },
  {
    "writing_date": "2025-08-24",
    "word_count": 145698,
    "words_written": 3503,
    "previous_date": "2025-08-23",
    "previous_count": 142195
  },
  {
    "writing_date": "2025-08-25",
    "word_count": 40329,
    "words_written": 0,
    "previous_date": "2025-08-24",
    "previous_count": 61558
  },
  {
    "writing_date": "2025-08-26",
    "word_count": 40435,
    "words_written": 106,
    "previous_date": "2025-08-25",
    "previous_count": 40329
  },
  {
    "writing_date": "2025-08-27",
    "word_count": 42158,
    "words_written": 1723,
    "previous_date": "2025-08-26",
    "previous_count": 40435
  },
  {
    "writing_date": "2025-08-28",
    "word_count": 42265,
    "words_written": 107,
    "previous_date": "2025-08-27",
    "previous_count": 42158
  },
  {
    "writing_date": "2025-08-29",
    "word_count": 42265,
    "words_written": 0,
    "previous_date": "2025-08-28",
    "previous_count": 42265
  },
  {
    "writing_date": "2025-08-30",
    "word_count": 42265,
    "words_written": 0,
    "previous_date": "2025-08-29",
    "previous_count": 42265
  },
  {
    "writing_date": "2025-08-31",
    "word_count": 42373,
    "words_written": 108,
    "previous_date": "2025-08-30",
    "previous_count": 42265
  },
  {
    "writing_date": "2025-09-01",
    "word_count": 42360,
    "words_written": 0,
    "previous_date": "2025-08-31",
    "previous_count": 42373
  },
  {
    "writing_date": "2025-09-02",
    "word_count": 42801,
    "words_written": 441,
    "previous_date": "2025-09-01",
    "previous_count": 42360
  },
  {
    "writing_date": "2025-09-03",
    "word_count": 44690,
    "words_written": 1889,
    "previous_date": "2025-09-02",
    "previous_count": 42801
  },
  {
    "writing_date": "2025-09-04",
    "word_count": 44699,
    "words_written": 9,
    "previous_date": "2025-09-03",
    "previous_count": 44690
  },
  {
    "writing_date": "2025-09-05",
    "word_count": 44625,
    "words_written": 0,
    "previous_date": "2025-09-04",
    "previous_count": 44699
  },
  {
    "writing_date": "2025-09-06",
    "word_count": 44628,
    "words_written": 3,
    "previous_date": "2025-09-05",
    "previous_count": 44625
  },
  {
    "writing_date": "2025-09-07",
    "word_count": 44707,
    "words_written": 79,
    "previous_date": "2025-09-06",
    "previous_count": 44628
  },
  {
    "writing_date": "2025-09-08",
    "word_count": 33851,
    "words_written": 0,
    "previous_date": "2025-09-07",
    "previous_count": 44707
  },
  {
    "writing_date": "2025-09-09",
    "word_count": 33851,
    "words_written": 0,
    "previous_date": "2025-09-08",
    "previous_count": 33851
  },
  {
    "writing_date": "2025-09-10",
    "word_count": 33851,
    "words_written": 0,
    "previous_date": "2025-09-09",
    "previous_count": 33851
  },
  {
    "writing_date": "2025-09-11",
    "word_count": 34269,
    "words_written": 418,
    "previous_date": "2025-09-10",
    "previous_count": 33851
  },
  {
    "writing_date": "2025-09-12",
    "word_count": 34269,
    "words_written": 0,
    "previous_date": "2025-09-11",
    "previous_count": 34269
  },
  {
    "writing_date": "2025-09-13",
    "word_count": 34269,
    "words_written": 0,
    "previous_date": "2025-09-12",
    "previous_count": 34269
  },
  {
    "writing_date": "2025-09-14",
    "word_count": 34269,
    "words_written": 0,
    "previous_date": "2025-09-13",
    "previous_count": 34269
  },
  {
    "writing_date": "2025-09-15",
    "word_count": 34269,
    "words_written": 0,
    "previous_date": "2025-09-14",
    "previous_count": 34269
  },
  {
    "writing_date": "2025-09-16",
    "word_count": 34269,
    "words_written": 0,
    "previous_date": "2025-09-15",
    "previous_count": 34269
  },
  {
    "writing_date": "2025-09-17",
    "word_count": 34269,
    "words_written": 0,
    "previous_date": "2025-09-16",
    "previous_count": 34269
  },
  {
    "writing_date": "2025-09-18",
    "word_count": 34269,
    "words_written": 0,
    "previous_date": "2025-09-17",
    "previous_count": 34269
  },
  {
    "writing_date": "2025-09-19",
    "word_count": 34269,
    "words_written": 0,
    "previous_date": "2025-09-18",
    "previous_count": 34269
  },
  {
    "writing_date": "2025-09-20",
    "word_count": 34269,
    "words_written": 0,
    "previous_date": "2025-09-19",
    "previous_count": 34269
  },
  {
    "writing_date": "2025-09-21",
    "word_count": 34269,
    "words_written": 0,
    "previous_date": "2025-09-20",
    "previous_count": 34269
  },
  {
    "writing_date": "2025-09-22",
    "word_count": 34269,
    "words_written": 0,
    "previous_date": "2025-09-21",
    "previous_count": 34269
  },
  {
    "writing_date": "2025-09-23",
    "word_count": 34269,
    "words_written": 0,
    "previous_date": "2025-09-22",
    "previous_count": 34269
  },
  {
    "writing_date": "2025-09-24",
    "word_count": 34269,
    "words_written": 0,
    "previous_date": "2025-09-23",
    "previous_count": 34269
  },
  {
    "writing_date": "2025-09-25",
    "word_count": 36549,
    "words_written": 2280,
    "previous_date": "2025-09-24",
    "previous_count": 34269
  },
  {
    "writing_date": "2025-09-26",
    "word_count": 36549,
    "words_written": 0,
    "previous_date": "2025-09-25",
    "previous_count": 36549
  },
  {
    "writing_date": "2025-09-27",
    "word_count": 36549,
    "words_written": 0,
    "previous_date": "2025-09-26",
    "previous_count": 36549
  },
  {
    "writing_date": "2025-09-28",
    "word_count": 36549,
    "words_written": 0,
    "previous_date": "2025-09-27",
    "previous_count": 36549
  },
  {
    "writing_date": "2025-09-29",
    "word_count": 36549,
    "words_written": 0,
    "previous_date": "2025-09-28",
    "previous_count": 36549
  },
  {
    "writing_date": "2025-09-30",
    "word_count": 36549,
    "words_written": 0,
    "previous_date": "2025-09-29",
    "previous_count": 36549
  },
  {
    "writing_date": "2025-10-01",
    "word_count": 36549,
    "words_written": 0,
    "previous_date": "2025-09-30",
    "previous_count": 36549
  },
  {
    "writing_date": "2025-10-02",
    "word_count": 40187,
    "words_written": 3638,
    "previous_date": "2025-10-01",
    "previous_count": 36549
  },
  {
    "writing_date": "2025-10-03",
    "word_count": 40904,
    "words_written": 717,
    "previous_date": "2025-10-02",
    "previous_count": 40187
  },
  {
    "writing_date": "2025-10-04",
    "word_count": 43370,
    "words_written": 2466,
    "previous_date": "2025-10-03",
    "previous_count": 40904
  },
  {
    "writing_date": "2025-10-05",
    "word_count": 43370,
    "words_written": 0,
    "previous_date": "2025-10-04",
    "previous_count": 43370
  },
  {
    "writing_date": "2025-10-06",
    "word_count": 44450,
    "words_written": 1080,
    "previous_date": "2025-10-05",
    "previous_count": 43370
  },
  {
    "writing_date": "2025-10-07",
    "word_count": 47630,
    "words_written": 3180,
    "previous_date": "2025-10-06",
    "previous_count": 44450
  },
  {
    "writing_date": "2025-10-08",
    "word_count": 51445,
    "words_written": 3815,
    "previous_date": "2025-10-07",
    "previous_count": 47630
  },
  {
    "writing_date": "2025-10-09",
    "word_count": 51766,
    "words_written": 321,
    "previous_date": "2025-10-08",
    "previous_count": 51445
  },
  {
    "writing_date": "2025-10-10",
    "word_count": 51876,
    "words_written": 110,
    "previous_date": "2025-10-09",
    "previous_count": 51766
  },
  {
    "writing_date": "2025-10-11",
    "word_count": 56336,
    "words_written": 4460,
    "previous_date": "2025-10-10",
    "previous_count": 51876
  },
  {
    "writing_date": "2025-10-12",
    "word_count": 56140,
    "words_written": 0,
    "previous_date": "2025-10-11",
    "previous_count": 56336
  },
  {
    "writing_date": "2025-10-13",
    "word_count": 56146,
    "words_written": 6,
    "previous_date": "2025-10-12",
    "previous_count": 56140
  },
  {
    "writing_date": "2025-10-14",
    "word_count": 56020,
    "words_written": 0,
    "previous_date": "2025-10-13",
    "previous_count": 56146
  },
  {
    "writing_date": "2025-10-15",
    "word_count": 56020,
    "words_written": 0,
    "previous_date": "2025-10-14",
    "previous_count": 56020
  },
  {
    "writing_date": "2025-10-16",
    "word_count": 55553,
    "words_written": 0,
    "previous_date": "2025-10-15",
    "previous_count": 56020
  },
  {
    "writing_date": "2025-10-17",
    "word_count": 55553,
    "words_written": 0,
    "previous_date": "2025-10-16",
    "previous_count": 55553
  },
  {
    "writing_date": "2025-10-18",
    "word_count": 55553,
    "words_written": 0,
    "previous_date": "2025-10-17",
    "previous_count": 55553
  },
  {
    "writing_date": "2025-10-19",
    "word_count": 55553,
    "words_written": 0,
    "previous_date": "2025-10-18",
    "previous_count": 55553
  },
  {
    "writing_date": "2025-10-20",
    "word_count": 55553,
    "words_written": 0,
    "previous_date": "2025-10-19",
    "previous_count": 55553
  },
  {
    "writing_date": "2025-10-21",
    "word_count": 55621,
    "words_written": 68,
    "previous_date": "2025-10-20",
    "previous_count": 55553
  },
  {
    "writing_date": "2025-10-22",
    "word_count": 55621,
    "words_written": 0,
    "previous_date": "2025-10-21",
    "previous_count": 55621
  },
  {
    "writing_date": "2025-10-23",
    "word_count": 55621,
    "words_written": 0,
    "previous_date": "2025-10-22",
    "previous_count": 55621
  },
  {
    "writing_date": "2025-10-24",
    "word_count": 55621,
    "words_written": 0,
    "previous_date": "2025-10-23",
    "previous_count": 55621
  },
  {
    "writing_date": "2025-10-25",
    "word_count": 55700,
    "words_written": 79,
    "previous_date": "2025-10-24",
    "previous_count": 55621
  },
  {
    "writing_date": "2025-10-26",
    "word_count": 55700,
    "words_written": 0,
    "previous_date": "2025-10-25",
    "previous_count": 55700
  },
  {
    "writing_date": "2025-10-27",
    "word_count": 55267,
    "words_written": 0,
    "previous_date": "2025-10-26",
    "previous_count": 55700
  },
  {
    "writing_date": "2025-10-28",
    "word_count": 55800,
    "words_written": 533,
    "previous_date": "2025-10-27",
    "previous_count": 55267
  },
  {
    "writing_date": "2025-10-29",
    "word_count": 55834,
    "words_written": 34,
    "previous_date": "2025-10-28",
    "previous_count": 55800
  },
  {
    "writing_date": "2025-10-30",
    "word_count": 55834,
    "words_written": 0,
    "previous_date": "2025-10-29",
    "previous_count": 55834
  },
  {
    "writing_date": "2025-10-31",
    "word_count": 60896,
    "words_written": 5062,
    "previous_date": "2025-10-30",
    "previous_count": 55834
  },
  {
    "writing_date": "2025-11-01",
    "word_count": 60896,
    "words_written": 0,
    "previous_date": "2025-10-31",
    "previous_count": 60896
  },
  {
    "writing_date": "2025-11-02",
    "word_count": 60896,
    "words_written": 0,
    "previous_date": "2025-11-01",
    "previous_count": 60896
  },
  {
    "writing_date": "2025-11-03",
    "word_count": 60896,
    "words_written": 0,
    "previous_date": "2025-11-02",
    "previous_count": 60896
  },
  {
    "writing_date": "2025-11-04",
    "word_count": 60896,
    "words_written": 0,
    "previous_date": "2025-11-03",
    "previous_count": 60896
  },
  {
    "writing_date": "2025-11-05",
    "word_count": 60896,
    "words_written": 0,
    "previous_date": "2025-11-04",
    "previous_count": 60896
  }
]